convert_csv_to_json/__init__.py
convert_csv_to_json/convert_csv_to_json.py
tests/__init__.py
tests/test_convert_csv_to_json.py
csv_to_list_of_dict-1.0.0.dist-info/LICENSE.txt
csv_to_list_of_dict-1.0.0.dist-info/METADATA
csv_to_list_of_dict-1.0.0.dist-info/WHEEL
csv_to_list_of_dict-1.0.0.dist-info/top_level.txt
csv_to_list_of_dict-1.0.0.dist-info/RECORD
