Metadata-Version: 2.1
Name: csv_to_list_of_dict
Version: 1.0.0
Summary: A simple Python package that converts csv file to a list of dictionaries
Home-page: https://github.com/micdurodola/convert_csv_to_json
Author: Micheal Durodola
Author-email: micdurodola@gmail.com
Project-URL: Bug Tracker, https://github.com/micdurodola/convert_csv_to_json/issues
Project-URL: repository, https://github.com/micdurodola/convert_csv_to_json
Classifier: Programming Language :: Python :: 3
Classifier: License :: OSI Approved :: MIT License
Classifier: Operating System :: OS Independent
Requires-Python: >=3.6
License-File: LICENSE.txt
